langchain_noctis/__init__.py
langchain_noctis/config.py
langchain_noctis/factory.py
langchain_noctis/py.typed
langchain_noctis/registry.py
langchain_noctis/retrievers.py
langchain_noctis/sources/__init__.py
langchain_noctis/sources/base.py
langchain_noctis/sources/domain_info.py
langchain_noctis/sources/domain_name_servers.py
langchain_noctis/sources/enums.py
langchain_noctis/sources/ip_sharing_domains.py
langchain_noctis/sources/mail_servers.py
langchain_noctis/sources/network_prefix_domains.py
langchain_noctis/sources/organization_domains.py
langchain_noctis/tools.py
langchain_noctis/utils.py
langchain_noctis-1.0.1b2.dist-info/LICENSE
langchain_noctis-1.0.1b2.dist-info/METADATA
langchain_noctis-1.0.1b2.dist-info/WHEEL
langchain_noctis-1.0.1b2.dist-info/RECORD
