Metadata-Version: 2.3
Name: langchain-noctis
Version: 1.0.1b2
Summary: An integration package connecting Noctis API and LangChain
License: MIT
Keywords: langchain,noctis,domain,dns,security,ai,retriever,llm,tool
Author: Noctis Team
Author-email: support@noctis.io
Requires-Python: >=3.9,<4.0
Classifier: Development Status :: 4 - Beta
Classifier: Intended Audience :: Developers
Classifier: Intended Audience :: Information Technology
Classifier: Intended Audience :: Science/Research
Classifier: Intended Audience :: Telecommunications Industry
Classifier: License :: OSI Approved :: MIT License
Classifier: Programming Language :: Python :: 3
Classifier: Programming Language :: Python :: 3.9
Classifier: Programming Language :: Python :: 3.10
Classifier: Programming Language :: Python :: 3.11
Classifier: Programming Language :: Python :: 3.12
Classifier: Programming Language :: Python :: 3.13
Classifier: Topic :: Internet
Classifier: Topic :: Security
Classifier: Topic :: Software Development :: Libraries
Classifier: Topic :: Software Development :: Libraries :: Python Modules
Requires-Dist: langchain-core (>=0.3.51,<0.4.0)
Requires-Dist: noctis_sdk (>=0.0.3,<0.0.4)
Project-URL: Bug Tracker, https://github.com/NoctisNet/langchain-noctis/issues
Project-URL: Changelog, https://github.com/NoctisNet/langchain-noctis/CHANGELOG.md
Project-URL: Documentation, https://github.com/NoctisNet/langchain-noctis/blob/main/architecture/README.md
Project-URL: HomePage, https://www.noctisnet.com/
Project-URL: Repository, https://github.com/NoctisNet/langchain-noctis
Project-URL: Release Notes, https://github.com/NoctisNet/langchain-noctis/releases
Project-URL: Source Code, https://github.com/NoctisNet/langchain-noctis
